endstone_welcome_message/__init__.py
endstone_welcome_message/config.toml
endstone_welcome_message/welcome_message.py
endstone_welcome_message-0.2.1.dist-info/METADATA
endstone_welcome_message-0.2.1.dist-info/WHEEL
endstone_welcome_message-0.2.1.dist-info/entry_points.txt
endstone_welcome_message-0.2.1.dist-info/licenses/LICENSE
endstone_welcome_message-0.2.1.dist-info/RECORD
