Metadata-Version: 2.4
Name: endstone-welcome-message
Version: 0.2.1
Summary: A simple plugin for Endstone that sends a welcome message to players when they join. The message can be shown in chat, tip, popup, toast, title, or form format.
Project-URL: Homepage, https://github.com/cenk/endstone-welcome-message
Project-URL: Documentation, https://github.com/cenk/endstone-welcome-message/blob/main/README.md
Project-URL: Issues, https://github.com/cenk/endstone-welcome-message/issues
Author-email: cenk <cenk@cenk.app>
License: MIT License
License-File: LICENSE
Keywords: bedrock,chat,endstone,form,message,minecraft,plugin,popup,tip,title,toast,welcome
Requires-Python: >=3.9
